README.rst
setup.py
pytopcmd/__init__.py
pytopcmd.egg-info/PKG-INFO
pytopcmd.egg-info/SOURCES.txt
pytopcmd.egg-info/dependency_links.txt
pytopcmd.egg-info/entry_points.txt
pytopcmd.egg-info/requires.txt
pytopcmd.egg-info/top_level.txt
pytopcmd.egg-info/zip-safe