Metadata-Version: 1.1
Name: pytopcmd
Version: 15
Summary: Simpler Unix top command implemented in python
Home-page: https://github.com/erikdejonge/pytop
Author: Erik de Jonge
Author-email: erik@a8.nl
License: GPL
Platform: UNKNOWN
Classifier: Programming Language :: Python :: 2
Classifier: Intended Audience :: Developers
Classifier: Intended Audience :: System Administrators
Classifier: Topic :: Utilities
Classifier: License :: OSI Approved :: GNU Library or Lesser General Public License (LGPL)
Classifier: Operating System :: POSIX
Classifier: Environment :: MacOS X
Classifier: Topic :: System
